censys/cloud_connectors/__init__.py
censys/cloud_connectors/aws_connector/__init__.py
censys/cloud_connectors/aws_connector/connector.py
censys/cloud_connectors/aws_connector/enums.py
censys/cloud_connectors/aws_connector/provider_setup.py
censys/cloud_connectors/aws_connector/serverless.py
censys/cloud_connectors/aws_connector/service.py
censys/cloud_connectors/aws_connector/settings.py
censys/cloud_connectors/azure_connector/__init__.py
censys/cloud_connectors/azure_connector/connector.py
censys/cloud_connectors/azure_connector/enums.py
censys/cloud_connectors/azure_connector/provider_setup.py
censys/cloud_connectors/azure_connector/settings.py
censys/cloud_connectors/common/__init__.py
censys/cloud_connectors/common/cli/__init__.py
censys/cloud_connectors/common/cli/args.py
censys/cloud_connectors/common/cli/base.py
censys/cloud_connectors/common/cli/commands/__init__.py
censys/cloud_connectors/common/cli/commands/config.py
censys/cloud_connectors/common/cli/commands/scan.py
censys/cloud_connectors/common/cli/provider_setup.py
censys/cloud_connectors/common/cloud_asset.py
censys/cloud_connectors/common/connector.py
censys/cloud_connectors/common/context.py
censys/cloud_connectors/common/enums.py
censys/cloud_connectors/common/healthcheck.py
censys/cloud_connectors/common/ignore_list.py
censys/cloud_connectors/common/logger.py
censys/cloud_connectors/common/models.py
censys/cloud_connectors/common/plugins/__init__.py
censys/cloud_connectors/common/plugins/events.py
censys/cloud_connectors/common/plugins/plugin.py
censys/cloud_connectors/common/plugins/registry.py
censys/cloud_connectors/common/seed.py
censys/cloud_connectors/common/settings.py
censys/cloud_connectors/gcp_connector/__init__.py
censys/cloud_connectors/gcp_connector/connector.py
censys/cloud_connectors/gcp_connector/enums.py
censys/cloud_connectors/gcp_connector/provider_setup.py
censys/cloud_connectors/gcp_connector/settings.py
censys/cloud_connectors/plugins/__init__.py
censys_cloud_connectors-3.2.1.dist-info/LICENSE
censys_cloud_connectors-3.2.1.dist-info/METADATA
censys_cloud_connectors-3.2.1.dist-info/WHEEL
censys_cloud_connectors-3.2.1.dist-info/entry_points.txt
censys_cloud_connectors-3.2.1.dist-info/RECORD
