Metadata-Version: 2.1
Name: censys-cloud-connectors
Version: 3.2.1
Summary: The Censys Unified Cloud Connector is a standalone connector that gathers assets from various cloud providers and stores them in Censys ASM.
License: Apache-2.0
Keywords: censys,cloud,connector,attack surface management
Author: Censys, Inc.
Author-email: support@censys.io
Requires-Python: >=3.9,<4.0
Classifier: Development Status :: 5 - Production/Stable
Classifier: Environment :: Console
Classifier: Intended Audience :: Information Technology
Classifier: Intended Audience :: System Administrators
Classifier: License :: OSI Approved :: Apache Software License
Classifier: Natural Language :: English
Classifier: Operating System :: OS Independent
Classifier: Programming Language :: Python
Classifier: Programming Language :: Python :: 3
Classifier: Programming Language :: Python :: 3.9
Classifier: Programming Language :: Python :: 3.10
Classifier: Programming Language :: Python :: 3.11
Classifier: Programming Language :: Python :: 3 :: Only
Classifier: Topic :: Internet
Classifier: Topic :: Security
Classifier: Topic :: System :: Monitoring
Classifier: Topic :: System :: Networking
Classifier: Topic :: System :: Networking :: Monitoring
Classifier: Topic :: Utilities
Classifier: Typing :: Typed
Requires-Dist: backoff (>=2.2.1,<3.0.0)
Requires-Dist: censys (>=2.2.4,<3.0.0)
Requires-Dist: inquirerpy (>=0.3.3,<0.4.0)
Requires-Dist: protobuf (>=4.23.4,<5.0.0)
Requires-Dist: pydantic[dotenv,email] (>=1.9.0,<2.0.0)
Requires-Dist: requests (>=2.30.0,<3.0.0)
Requires-Dist: rich (>=13.3.5,<14.0.0)
Project-URL: Censys Homepage, https://censys.io/
Project-URL: Changelog, https://github.com/censys/censys-cloud-connector/releases
Project-URL: Discussions, https://github.com/censys/censys-cloud-connector/discussions
Project-URL: Source, https://github.com/censys/censys-cloud-connector
Project-URL: Tracker, https://github.com/censys/censys-cloud-connector/issues
